quickweatherinfo
